[{"end_time":"Fri, 05 Feb 2021 00:29:50 GMT","end_time_unix_timestamp":1612484990,"grade":"F","scan_id":17591316,"score":0},{"end_time":"Fri, 30 Jul 2021 00:06:58 GMT","end_time_unix_timestamp":1627603618,"grade":"F","scan_id":20539980,"score":5},{"end_time":"Wed, 11 May 2022 03:11:55 GMT","end_time_unix_timestamp":1652238715,"grade":"D-","scan_id":26363688,"score":25},{"end_time":"Mon, 26 Sep 2022 01:06:16 GMT","end_time_unix_timestamp":1664154376,"grade":"F","scan_id":29659095,"score":5},{"end_time":"Tue, 27 Sep 2022 01:09:02 GMT","end_time_unix_timestamp":1664240942,"grade":"D-","scan_id":29689493,"score":25}]