{
  "algorithm_version": 2,
  "end_time": "Mon, 14 Mar 2022 00:41:54 GMT",
  "grade": "F",
  "hidden": false,
  "likelihood_indicator": "MEDIUM",
  "response_headers": {
    "Connection": "Keep-Alive",
    "Content-Encoding": "gzip",
    "Content-Type": "text/html;charset=UTF-8",
    "Date": "Mon, 14 Mar 2022 00:41:33 GMT",
    "Keep-Alive": "timeout=15, max=500",
    "Referrer-Policy": "origin-when-cross-origin,strict-origin-when-cross-origin",
    "Server": "Microsoft-IIS/5.0",
    "Server-Timing": "dtSInfo;desc=\"0\", dtRpid;desc=\"926315144\"",
    "Set-Cookie": "NEW_VISITOR=new; Expires=Tue, 15-Mar-2022 00:41:33 GMT; HttpOnly; Secure; SameSite=None, VISITOR=returning; Path=/pag_Home/index.html; HttpOnly; Secure; SameSite=None, JSESSIONID=DBE16F9A74129ED536BCCCE1FFC4C139; Path=/; Secure; HttpOnly; SameSite=None, dtCookie=v_4_srv_4_sn_0CF9458F079DDB05A9D3A984FA2CCB4C_perc_100000_ol_0_mul_1_app-3A7bd681314de07953_0; Path=/; Domain=.administracion.gob.es; HttpOnly; Secure; SameSite=None, TS01a8e1d0=01d9c3d318f6fc59927dddefaa3753d03748f06383ce797476756385a64253ec647ad84d60b5185ac80b551df05c7ea1003d6c92a1c232493298e4d7d0bdcbb9c79aac3c160bb26041ded81331b8a38dbd22efe5ea; Path=/; HttpOnly; Secure; SameSite=None, TS013cc2a2=01d9c3d318cda2400825926918c31562952d9e4195ce797476756385a64253ec647ad84d6030e305c29772ba7c2d7ac9a2d7228e5e2d24a5beaea812a4821df7752ac7a698; path=/pag_Home/index.html; HttpOnly; Secure; SameSite=None, TS011faf93=01d9c3d31862fd53f015bd166181252fbaf1aa0657ce797476756385a64253ec647ad84d60c1cc6921007878209c3a17e6c4bb02b5a5b4dbbc17d56e1061dff258fa1da4ed; path=/; domain=.administracion.gob.es; HttpOnly; Secure; SameSite=None",
    "Strict-Transport-Security": "max-age=63072000; preload",
    "Transfer-Encoding": "chunked",
    "Vary": "Accept-Encoding",
    "X-Content-Type-Options": "nosniff",
    "X-Frame-Options": "SAMEORIGIN",
    "X-OneAgent-JS-Injection": "true, true",
    "X-XSS-Protection": "1;mode=block"
  },
  "scan_id": 25123160,
  "score": 5,
  "start_time": "Mon, 14 Mar 2022 00:41:29 GMT",
  "state": "FINISHED",
  "status_code": 200,
  "tests_failed": 3,
  "tests_passed": 9,
  "tests_quantity": 12
}