{
  "id": 75000847,
  "algorithm_version": 4,
  "scanned_at": "2025-10-15T01:00:42.784Z",
  "error": null,
  "grade": "D",
  "response_headers": {
    "via": "1.1 0d07c64d85b9f0560eabd0b323a4bf58.cloudfront.net (CloudFront)",
    "date": "Wed, 15 Oct 2025 01:00:44 GMT",
    "etag": "W/\"eaa34d7d0ff667fed4e2935f37111d28\"",
    "vary": "accept-encoding",
    "server": "AmazonS3",
    "x-cache": "RefreshHit from cloudfront",
    "connection": "close",
    "x-amz-cf-id": "8REWXFFqI2PQuLGGZpLLMrlAfNnT41UhW0lFdqwmSODNRlbQk-4WQg==",
    "content-type": "text/html",
    "x-amz-cf-pop": "SEA900-P2",
    "last-modified": "Mon, 13 Oct 2025 09:04:28 GMT",
    "transfer-encoding": "chunked",
    "x-amz-server-side-encryption": "AES256"
  },
  "score": 30,
  "status_code": 200,
  "tests_failed": 4,
  "tests_passed": 6,
  "tests_quantity": 10
}