{
  "id": 92280462,
  "algorithm_version": 5,
  "scanned_at": "2026-04-16T01:58:40.241Z",
  "error": null,
  "grade": "D",
  "response_headers": {
    "via": "1.1 884680276f0c3ab3c1a683a7d44cb4c6.cloudfront.net (CloudFront)",
    "date": "Thu, 16 Apr 2026 01:58:41 GMT",
    "etag": "W/\"10961be11dfff77cd516ee64ee7315c9\"",
    "vary": "Accept-Encoding",
    "server": "AmazonS3",
    "x-cache": "RefreshHit from cloudfront",
    "connection": "close",
    "x-amz-cf-id": "d-eRD1_giu8aSKVYpG4e8LUrWrqZGJvNlbP8El8AVy7hwNRVS4CmXA==",
    "content-type": "text/html",
    "x-amz-cf-pop": "SEA73-P3",
    "last-modified": "Thu, 09 Apr 2026 12:15:56 GMT",
    "transfer-encoding": "chunked",
    "x-amz-server-side-encryption": "AES256"
  },
  "score": 30,
  "status_code": 200,
  "tests_failed": 4,
  "tests_passed": 6,
  "tests_quantity": 10
}