{
  "algorithm_version": 2,
  "end_time": "Sat, 02 Apr 2022 00:44:21 GMT",
  "grade": "F",
  "hidden": false,
  "likelihood_indicator": "MEDIUM",
  "response_headers": {
    "Accept-Ranges": "bytes",
    "Connection": "Keep-Alive",
    "Content-Encoding": "gzip",
    "Content-Length": "9506",
    "Content-Type": "text/html; charset=utf-8",
    "Date": "Sat, 02 Apr 2022 00:44:19 GMT",
    "ETag": "\"8ab7-5db983d6435f6-gzip\"",
    "Keep-Alive": "timeout=5, max=100",
    "Last-Modified": "Fri, 01 Apr 2022 14:03:15 GMT",
    "Server": "Apache/2.4.52 (Debian)",
    "Set-Cookie": "cookiesession1=678B2889UV0123456789890123AB0FC1;Expires=Sun, 02 Apr 2023 00:44:19 GMT;Path=/;HttpOnly",
    "Strict-Transport-Security": "max-age=15552000; includeSubDomains",
    "Vary": "Accept-Encoding"
  },
  "scan_id": 25556570,
  "score": 10,
  "start_time": "Sat, 02 Apr 2022 00:42:16 GMT",
  "state": "FINISHED",
  "status_code": 200,
  "tests_failed": 6,
  "tests_passed": 6,
  "tests_quantity": 12
}