{
  "id": 70786582,
  "algorithm_version": 4,
  "scanned_at": "2025-08-22T01:02:01.921Z",
  "error": null,
  "grade": "F",
  "response_headers": {
    "age": "0",
    "date": "Fri, 22 Aug 2025 01:02:06 GMT",
    "vary": "Accept-Encoding,Cookie",
    "pragma": "no-cache",
    "server": "HTTPd",
    "expires": "Thu, 19 Nov 1981 08:52:00 GMT",
    "connection": "close",
    "set-cookie": "PHPSESSID=e06c71e31e38f03ea37995a189368b0b; path=/",
    "content-type": "text/html; charset=UTF-8",
    "accept-ranges": "bytes",
    "cache-control": "no-store, no-cache, must-revalidate",
    "content-length": "30883"
  },
  "score": 0,
  "status_code": 200,
  "tests_failed": 6,
  "tests_passed": 4,
  "tests_quantity": 10
}