{
  "id": 80618997,
  "algorithm_version": 5,
  "scanned_at": "2025-12-19T01:08:16.760Z",
  "error": null,
  "grade": "F",
  "response_headers": {
    "date": "Fri, 19 Dec 2025 01:08:17 GMT",
    "etag": "W/\"1766100314-0\"",
    "link": "<https://concellodelugo.gal/gl>; rel=\"canonical\",<https://concellodelugo.gal/gl>; rel=\"shortlink\"",
    "vary": "Cookie",
    "server": "nginx",
    "expires": "Fri, 19 Dec 2025 02:08:17 GMT",
    "connection": "close",
    "set-cookie": "cookiesession1=678A3E0F51A9D42AD53175D9496F3E69;Expires=Sat, 19 Dec 2026 01:08:17 GMT;Path=/;HttpOnly",
    "content-type": "text/html; charset=utf-8",
    "x-powered-by": "PHP/5.6.40",
    "cache-control": "max-age=3600",
    "last-modified": "Thu, 18 Dec 2025 23:25:14 GMT",
    "content-length": "32566",
    "x-ua-compatible": "IE=edge,chrome=1",
    "content-language": "gl",
    "x-xss-protection": "1",
    "access-control-allow-origin": "*"
  },
  "score": 0,
  "status_code": 200,
  "tests_failed": 6,
  "tests_passed": 4,
  "tests_quantity": 10
}