{
  "algorithm_version": 2,
  "end_time": "Thu, 17 Mar 2022 00:42:41 GMT",
  "grade": "F",
  "hidden": false,
  "likelihood_indicator": "MEDIUM",
  "response_headers": {
    "Access-Control-Allow-Origin": "*",
    "Cache-Control": "max-age=3600",
    "Connection": "keep-alive",
    "Content-Encoding": "gzip",
    "Content-Language": "gl",
    "Content-Type": "text/html; charset=utf-8",
    "Date": "Thu, 17 Mar 2022 00:42:03 GMT",
    "Etag": "W/\"1647460543-0\"",
    "Expires": "Thu, 17 Mar 2022 01:42:03 GMT",
    "Last-Modified": "Wed, 16 Mar 2022 19:55:43 +0000",
    "Link": "<http://concellodelugo.gal/gl>; rel=\"canonical\",<http://concellodelugo.gal/gl>; rel=\"shortlink\"",
    "Server": "nginx",
    "Transfer-Encoding": "chunked",
    "Vary": "Cookie",
    "X-UA-Compatible": "IE=edge,chrome=1"
  },
  "scan_id": 25214708,
  "score": 0,
  "start_time": "Thu, 17 Mar 2022 00:42:01 GMT",
  "state": "FINISHED",
  "status_code": 200,
  "tests_failed": 8,
  "tests_passed": 4,
  "tests_quantity": 12
}