{
  "algorithm_version": 2,
  "end_time": "Fri, 26 Aug 2022 01:01:59 GMT",
  "grade": "B",
  "hidden": false,
  "likelihood_indicator": "MEDIUM",
  "response_headers": {
    "CF-Cache-Status": "DYNAMIC",
    "CF-RAY": "7408a23b4d429450-SJC",
    "Cache-Control": "no-cache",
    "Connection": "keep-alive",
    "Content-Encoding": "gzip",
    "Content-Type": "text/html; charset=UTF-8",
    "Date": "Fri, 26 Aug 2022 01:01:00 GMT",
    "Expect-CT": "max-age=604800, report-uri=\"https://report-uri.cloudflare.com/cdn-cgi/beacon/expect-ct\"",
    "Last-Modified": "Thu, 25 Aug 2022 21:30:41 GMT",
    "NEL": "{\"success_fraction\":0,\"report_to\":\"cf-nel\",\"max_age\":604800}",
    "Referrer-Policy": "strict-origin",
    "Report-To": "{\"endpoints\":[{\"url\":\"https:\\/\\/a.nel.cloudflare.com\\/report\\/v3?s=Fp1Z786PsaVoUbI6NOhznc1O9RcTNGWRrXveR%2FySrrVupgSB6%2BZWjYSyZT45Y1fXCd%2FC7D7r76olnHD5Wq22Q%2FU1z0UCwCwTMrrzwF4ukVu0Mm8V7LwCk1sunaUtK72hDP149VbECpVmxDPqr3BLbzwyI72BM%2BwVW6Bp\"}],\"group\":\"cf-nel\",\"max_age\":604800}",
    "Server": "cloudflare",
    "Strict-Transport-Security": "max-age=31536000; includeSubDomains; preload",
    "Transfer-Encoding": "chunked",
    "Vary": "User-Agent",
    "WPO-Cache-Status": "cached",
    "X-Content-Type-Options": "nosniff",
    "X-Frame-Options": "sameorigin",
    "X-XSS-Protection": "1;  mode=block",
    "alt-svc": "h3=\":443\"; ma=86400, h3-29=\":443\"; ma=86400"
  },
  "scan_id": 28965585,
  "score": 75,
  "start_time": "Fri, 26 Aug 2022 01:00:57 GMT",
  "state": "FINISHED",
  "status_code": 200,
  "tests_failed": 1,
  "tests_passed": 11,
  "tests_quantity": 12
}