{
  "algorithm_version": 2,
  "end_time": "Sat, 30 Apr 2022 00:11:51 GMT",
  "grade": "F",
  "hidden": false,
  "likelihood_indicator": "MEDIUM",
  "response_headers": {
    "Content-Length": "799",
    "Content-Type": "text/html",
    "Date": "Sat, 30 Apr 2022 00:11:45 GMT",
    "Server": "Microsoft-IIS/8.5",
    "X-Powered-By": "ASP.NET",
    "X-Powered-By-Plesk": "PleskWin"
  },
  "scan_id": 26128528,
  "score": 20,
  "start_time": "Sat, 30 Apr 2022 00:11:45 GMT",
  "state": "FINISHED",
  "status_code": 200,
  "tests_failed": 5,
  "tests_passed": 7,
  "tests_quantity": 12
}