{
  "algorithm_version": 3,
  "end_time": "Fri, 11 Oct 2024 00:14:37 GMT",
  "grade": "F",
  "hidden": false,
  "likelihood_indicator": "MEDIUM",
  "response_headers": {
    "Cache-Control": "private, no-cache, no-store, must-revalidate",
    "Connection": "Keep-Alive",
    "Content-Length": "51387",
    "Content-Type": "text/html; charset=UTF-8",
    "Date": "Fri, 11 Oct 2024 00:14:35 GMT",
    "ETag": "\"e9b14817\"",
    "Expires": "Thu, 01 Jan 1970 00:00:00 GMT",
    "Keep-Alive": "timeout=5, max=99",
    "Liferay-Portal": "Liferay Digital Experience Platform",
    "Pragma": "no-cache",
    "Server": "Apache",
    "Set-Cookie": "JSESSIONID=Qmh47V_whfpeG3MBGd_rR0MuODW5zSAaBcKD80Q4Q9IO1fCAGDjO!-1121964485; path=/; HttpOnly, QueueITAccepted-SDFrts345E-V3_lmsr=EventId%3Dlmsr%26QueueId%3D92a0ce21-fe32-40f2-b780-9f756050ff88%26RedirectType%3Dsafetynet%26IssueTime%3D1728605675%26Hash%3D7ab4f611aa07ac11ff97cd3406636bb4e553c77933f5a1f6e7a9145a81450a7d; expires=Sat, 12-Oct-2024 00:14:35 GMT; path=/; HttpOnly, COOKIE_SUPPORT=true; expires=Sat, 11-Oct-2025 00:14:35 GMT; path=/; secure; HttpOnly, GUEST_LANGUAGE_ID=ca_ES; domain=.gencat.cat; expires=Sat, 11-Oct-2025 00:14:35 GMT; path=/; secure; HttpOnly, QueueITAccepted-SDFrts345E-V3_lmsr=EventId%3Dlmsr%26QueueId%3D92a0ce21-fe32-40f2-b780-9f756050ff88%26RedirectType%3Dsafetynet%26IssueTime%3D1728605675%26Hash%3D7ab4f611aa07ac11ff97cd3406636bb4e553c77933f5a1f6e7a9145a81450a7d; expires=Sat, 12-Oct-2024 00:14:35 GMT; path=/; HttpOnly, COOKIE_SUPPORT=true; expires=Sat, 11-Oct-2025 00:14:35 GMT; path=/; secure; HttpOnly, GUEST_LANGUAGE_ID=ca_ES; domain=.gencat.cat; expires=Sat, 11-Oct-2025 00:14:35 GMT; path=/; secure; HttpOnly",
    "X-Content-Type-Options": "nosniff",
    "X-Frame-Options": "SAMEORIGIN",
    "X-XSS-Protection": "1"
  },
  "scan_id": 56705441,
  "score": 15,
  "start_time": "Fri, 11 Oct 2024 00:14:31 GMT",
  "state": "FINISHED",
  "status_code": 200,
  "tests_failed": 3,
  "tests_passed": 7,
  "tests_quantity": 10
}