{
  "algorithm_version": 2,
  "end_time": "Sun, 09 Jan 2022 00:35:41 GMT",
  "grade": "F",
  "hidden": false,
  "likelihood_indicator": "MEDIUM",
  "response_headers": {
    "Connection": "close",
    "Content-Language": "es-ES",
    "Content-Length": "4881",
    "Content-Type": "text/html;charset=utf-8",
    "Date": "Sun, 09 Jan 2022 00:35:19 GMT",
    "Server": "Apache"
  },
  "scan_id": 23767146,
  "score": 0,
  "start_time": "Sun, 09 Jan 2022 00:35:06 GMT",
  "state": "FINISHED",
  "status_code": 200,
  "tests_failed": 7,
  "tests_passed": 5,
  "tests_quantity": 12
}