{
  "algorithm_version": 2,
  "end_time": "Mon, 23 May 2022 00:50:17 GMT",
  "grade": "D-",
  "hidden": false,
  "likelihood_indicator": "MEDIUM",
  "response_headers": {
    "Accept-Ranges": "bytes",
    "Age": "0",
    "Cache-Control": "max-age=600",
    "Connection": "keep-alive",
    "Content-Encoding": "gzip",
    "Content-Language": "en",
    "Content-Length": "87126",
    "Content-Type": "text/html;charset=UTF-8",
    "Date": "Mon, 23 May 2022 00:50:09 GMT",
    "Server": "Apache",
    "Strict-Transport-Security": "max-age=31557600",
    "Vary": "Accept-Encoding",
    "Via": "1.1 varnish",
    "X-Cache": "MISS",
    "X-Cache-Hits": "0",
    "X-Served-By": "cache-pao17438-PAO",
    "X-Timer": "S1653267006.133290,VS0,VE3287"
  },
  "scan_id": 26608775,
  "score": 25,
  "start_time": "Mon, 23 May 2022 00:50:00 GMT",
  "state": "FINISHED",
  "status_code": 200,
  "tests_failed": 6,
  "tests_passed": 6,
  "tests_quantity": 12
}