{
  "algorithm_version": 2,
  "end_time": "Wed, 30 Mar 2022 01:02:51 GMT",
  "grade": "F",
  "hidden": false,
  "likelihood_indicator": "MEDIUM",
  "response_headers": {
    "Age": "131",
    "Cache-Control": "max-age=10800",
    "Content-Encoding": "gzip",
    "Content-Length": "32551",
    "Content-Type": "text/html;charset=UTF-8",
    "Date": "Wed, 30 Mar 2022 01:02:25 GMT",
    "Expires": "Wed, 30 Mar 2022 04:02:25 GMT",
    "Last-Modified": "Tue, 29 Mar 2022 21:00:15 EDT",
    "Server": "ECAcc (saa/82A6)",
    "Vary": "Accept-Encoding",
    "X-Cache": "HIT"
  },
  "scan_id": 25485024,
  "score": 0,
  "start_time": "Wed, 30 Mar 2022 01:02:22 GMT",
  "state": "FINISHED",
  "status_code": 200,
  "tests_failed": 8,
  "tests_passed": 4,
  "tests_quantity": 12
}