{
  "algorithm_version": 2,
  "end_time": "Tue, 29 Aug 2023 00:08:49 GMT",
  "grade": "F",
  "hidden": false,
  "likelihood_indicator": "MEDIUM",
  "response_headers": {
    "Age": "629",
    "Cache-Control": "private",
    "Connection": "keep-alive",
    "Content-Encoding": "gzip",
    "Content-Type": "text/html; Charset=windows-1252",
    "Date": "Mon, 28 Aug 2023 23:58:18 GMT",
    "Set-Cookie": "idioma_www.alfarnatejo.es=es; path=/; Secure; HttpOnly; SameSite=Strict;, ASPSESSIONIDAQCFSSET=NKMIJNECLKJNLEFELAPDAICD; secure; path=/; HttpOnly; SameSite=Strict;",
    "Strict-Transport-Security": "max-age=31536000; includeSubDomains",
    "Transfer-Encoding": "chunked",
    "Vary": "Accept-Encoding",
    "Via": "1.1 68cbf66079d970fd8384ddd79f00d90e.cloudfront.net (CloudFront)",
    "X-Amz-Cf-Id": "Du27hMfmi3FPQZVfGw0Jz19EBnKXcmSmdaLOHiEQylPfqJNz144asA==",
    "X-Amz-Cf-Pop": "DEN50-C1",
    "X-Cache": "Hit from cloudfront",
    "X-Frame-Options": "ALLOW-FROM https://www.alfarnatejo.es/"
  },
  "scan_id": 41397239,
  "score": 0,
  "start_time": "Tue, 29 Aug 2023 00:08:35 GMT",
  "state": "FINISHED",
  "status_code": 200,
  "tests_failed": 5,
  "tests_passed": 7,
  "tests_quantity": 12
}