{
  "algorithm_version": 2,
  "end_time": "Fri, 24 Nov 2023 00:40:49 GMT",
  "grade": "C",
  "hidden": false,
  "likelihood_indicator": "MEDIUM",
  "response_headers": {
    "Cache-Control": "private, no-cache, no-store, must-revalidate",
    "Connection": "Keep-Alive",
    "Content-Encoding": "gzip",
    "Content-Length": "19939",
    "Content-Type": "text/html;charset=UTF-8",
    "Date": "Fri, 24 Nov 2023 00:40:46 GMT",
    "Expires": "Thu, 01 Jan 1970 00:00:00 GMT",
    "Keep-Alive": "timeout=5, max=100",
    "Liferay-Portal": "Liferay Digital Experience Platform 7.2.10 GA1 (Mueller / Build 7210 / May 13, 2019)",
    "Pragma": "no-cache",
    "Server": "Apache",
    "Set-Cookie": "JSESSIONID=9F2393233B987C9075E71046A0E8139B; Path=/; Secure; HttpOnly, COOKIE_SUPPORT=true; Max-Age=31536000; Expires=Sat, 23-Nov-2024 00:40:46 GMT; Path=/; Secure; HttpOnly, GUEST_LANGUAGE_ID=es_ES; Max-Age=31536000; Expires=Sat, 23-Nov-2024 00:40:46 GMT; Path=/; Secure; HttpOnly",
    "Vary": "Accept-Encoding",
    "X-Content-Type-Options": "nosniff",
    "X-Frame-Options": "ALLOW-FROM https://i-cast.viajesvirtualesweb.es/",
    "X-XSS-Protection": "1"
  },
  "scan_id": 44802100,
  "score": 55,
  "start_time": "Fri, 24 Nov 2023 00:40:33 GMT",
  "state": "FINISHED",
  "status_code": 200,
  "tests_failed": 2,
  "tests_passed": 10,
  "tests_quantity": 12
}