{
  "algorithm_version": 2,
  "end_time": "Sun, 24 Sep 2023 00:08:20 GMT",
  "grade": "F",
  "hidden": false,
  "likelihood_indicator": "MEDIUM",
  "response_headers": {
    "Age": "371",
    "Cache-Control": "private",
    "Connection": "keep-alive",
    "Content-Encoding": "gzip",
    "Content-Type": "text/html; Charset=windows-1252",
    "Date": "Sun, 24 Sep 2023 00:02:08 GMT",
    "Set-Cookie": "idioma_www.alfarnatejo.es=es; path=/; Secure; HttpOnly; SameSite=Strict;, ASPSESSIONIDCSAXTRTB=LNOLBBLDNKIAKJPKCINBPPAB; secure; path=/; HttpOnly; SameSite=Strict;",
    "Strict-Transport-Security": "max-age=31536000; includeSubDomains",
    "Transfer-Encoding": "chunked",
    "Vary": "Accept-Encoding",
    "Via": "1.1 ec4d04f2befcd6652834fd368a8b671e.cloudfront.net (CloudFront)",
    "X-Amz-Cf-Id": "fJsl14QHyZdoZcy9cywyNihNL2KNegjMRJbCFtQWUDbNgVGQx6Gp7Q==",
    "X-Amz-Cf-Pop": "DEN50-C2",
    "X-Cache": "Hit from cloudfront",
    "X-Frame-Options": "ALLOW-FROM https://www.alfarnatejo.es/"
  },
  "scan_id": 42499054,
  "score": 0,
  "start_time": "Sun, 24 Sep 2023 00:08:17 GMT",
  "state": "FINISHED",
  "status_code": 200,
  "tests_failed": 5,
  "tests_passed": 7,
  "tests_quantity": 12
}