{
  "algorithm_version": 2,
  "end_time": "Sat, 08 May 2021 00:21:01 GMT",
  "grade": "F",
  "hidden": false,
  "likelihood_indicator": "MEDIUM",
  "response_headers": {
    "Connection": "close",
    "Content-Type": "text/html; charset=utf-8",
    "Date": "Sat, 08 May 2021 00:27:47 GMT",
    "Server": "Apache/2.2.15 (CentOS)",
    "Set-Cookie": "fe_typo_user=aa0bd5c26bc6f98368177d636a2253a8; path=/",
    "Transfer-Encoding": "chunked",
    "X-Powered-By": "PHP/5.3.3"
  },
  "scan_id": 19054591,
  "score": 0,
  "start_time": "Sat, 08 May 2021 00:20:15 GMT",
  "state": "FINISHED",
  "status_code": 200,
  "tests_failed": 8,
  "tests_passed": 4,
  "tests_quantity": 12
}