{
  "id": 108850759,
  "algorithm_version": 5,
  "scanned_at": "2026-07-20T02:13:15.723Z",
  "error": null,
  "grade": "C+",
  "response_headers": {
    "date": "Mon, 20 Jul 2026 02:13:23 GMT",
    "pragma": "no-cache",
    "server": "Apache",
    "expires": "Thu, 01 Jan 1970 00:00:00 GMT",
    "connection": "close",
    "set-cookie": "JSESSIONID=6B7D3DCF08F018FC5FDC28842C1818CF.srt2; Path=/; Secure; HttpOnly,COOKIE_SUPPORT=true; Max-Age=31536000; Expires=Tue, 20 Jul 2027 02:13:16 GMT; Path=/; Secure; HttpOnly,GUEST_LANGUAGE_ID=es_ES; Max-Age=31536000; Expires=Tue, 20 Jul 2027 02:13:16 GMT; Path=/; Secure; HttpOnly,cookiesession1=678B28DE947743E046E0D5DCCEEB071A;Expires=Tue, 20 Jul 2027 02:13:22 GMT;Path=/;HttpOnly",
    "content-type": "text/html;charset=UTF-8",
    "cache-control": "private, no-cache, no-store, must-revalidate",
    "content-length": "109526",
    "liferay-portal": "Liferay Digital Experience Platform",
    "x-frame-options": "SAMEORIGIN",
    "x-xss-protection": "1",
    "x-content-type-options": "nosniff",
    "strict-transport-security": "max-age=31536000; includeSubDomains; preload"
  },
  "score": 60,
  "status_code": 200,
  "tests_failed": 3,
  "tests_passed": 7,
  "tests_quantity": 10
}