{
  "algorithm_version": 2,
  "end_time": "Tue, 14 Mar 2023 00:11:33 GMT",
  "grade": "F",
  "hidden": false,
  "likelihood_indicator": "MEDIUM",
  "response_headers": {
    "Age": "838",
    "Cache-Control": "private",
    "Connection": "keep-alive",
    "Content-Encoding": "gzip",
    "Content-Type": "text/html; Charset=windows-1252",
    "Date": "Mon, 13 Mar 2023 23:57:31 GMT",
    "Set-Cookie": "idioma_www.cartama.es=es; path=/; HttpOnly; Secure; SameSite=Strict, ASPSESSIONIDAARSXTDT=CDFEEDDDIFOAMGOBFGAKBKDB; secure; path=/",
    "Transfer-Encoding": "chunked",
    "Vary": "Accept-Encoding",
    "Via": "1.1 61729b32280fd6715c2a3b0dbb7e571a.cloudfront.net (CloudFront)",
    "X-Amz-Cf-Id": "nBMJZv23dc82lW5b6SiR7qbj9v9Ix3JOY9FceU8v-ArXSopYwGTFuw==",
    "X-Amz-Cf-Pop": "SFO5-C1",
    "X-Cache": "Hit from cloudfront",
    "X-Frame-Options": "ALLOW-FROM https://www.cartama.es/"
  },
  "scan_id": 35243618,
  "score": 0,
  "start_time": "Tue, 14 Mar 2023 00:11:25 GMT",
  "state": "FINISHED",
  "status_code": 200,
  "tests_failed": 6,
  "tests_passed": 6,
  "tests_quantity": 12
}