{
  "algorithm_version": 2,
  "end_time": "Tue, 04 Jan 2022 00:35:13 GMT",
  "grade": "B-",
  "hidden": false,
  "likelihood_indicator": "MEDIUM",
  "response_headers": {
    "Accept-Ranges": "bytes",
    "Age": "33",
    "Cache-Control": "max-age=900, public",
    "Content-Encoding": "gzip",
    "Content-Length": "28413",
    "Content-Type": "text/html; charset=UTF-8",
    "Content-language": "es",
    "Date": "Tue, 04 Jan 2022 00:33:51 GMT",
    "ETag": "\"1641256429-gzip\"",
    "Expires": "Sun, 19 Nov 1978 05:00:00 GMT",
    "Last-Modified": "Tue, 04 Jan 2022 00:33:49 GMT",
    "Link": "<https://www.holaislascanarias.com/>; rel=\"shortlink\", <https://www.holaislascanarias.com/>; rel=\"canonical\", <https://www.holaislascanarias.com/hola-desde-el-mejor-clima-del-mundo/>; rel=\"alternate\"; hreflang=\"es\", <https://www.hellocanaryislands.com/hello-from-the-best-climate-in-the-world/>; rel=\"alternate\"; hreflang=\"en\", <https://www.hallokanarischeinseln.com/hallo-aus-dem-besten-klima-der-welt/>; rel=\"alternate\"; hreflang=\"de\", <https://www.holaislascanarias.com/hola-desde-el-mejor-clima-del-mundo/>; rel=\"revision\"",
    "Strict-Transport-Security": "max-age=63072000",
    "Vary": "X-Bin,Accept-Encoding, Cookie",
    "X-Adv-Varnish": "Cache-enabled",
    "X-Cache-Age": "33",
    "X-Cache-Hits": "5",
    "X-Cache-TTL-Remaining": "2629712.833",
    "X-Cacheable": "YES",
    "X-Content-Type-Options": "nosniff",
    "X-Drupal-Cache": "MISS",
    "X-Frame-Options": "SAMEORIGIN",
    "X-Grace": "",
    "X-TTL": "2629746",
    "X-UA-Compatible": "IE=edge",
    "X-Varnish": "851313863 850014915",
    "X-Varnish-Cache": "HIT"
  },
  "scan_id": 23641548,
  "score": 65,
  "start_time": "Tue, 04 Jan 2022 00:33:28 GMT",
  "state": "FINISHED",
  "status_code": 200,
  "tests_failed": 2,
  "tests_passed": 10,
  "tests_quantity": 12
}