{
  "algorithm_version": 3,
  "end_time": "Sun, 16 Jun 2024 00:14:14 GMT",
  "grade": "F",
  "hidden": false,
  "likelihood_indicator": "MEDIUM",
  "response_headers": {
    "Cache-Control": "max-age=3600, public",
    "Content-Encoding": "gzip",
    "Content-Length": "21787",
    "Content-Type": "text/html; charset=UTF-8",
    "Date": "Sun, 16 Jun 2024 00:14:06 GMT",
    "ETag": "\"9d3d3a65bd0f4bc42d8ffac91ef3e9cd\"",
    "Expires": "Sun, 16 Jun 2024 01:14:06 GMT",
    "Last-Modified": "Sun, 16 Jun 2024 00:14:06 GMT",
    "Pragma": "public",
    "Server": "Microsoft-IIS/10.0",
    "Vary": "Accept-Encoding",
    "X-Powered-By": "PHP/8.0.30, ASP.NET"
  },
  "scan_id": 52312742,
  "score": 0,
  "start_time": "Sun, 16 Jun 2024 00:14:04 GMT",
  "state": "FINISHED",
  "status_code": 200,
  "tests_failed": 5,
  "tests_passed": 6,
  "tests_quantity": 11
}