{
  "id": 63336727,
  "algorithm_version": 4,
  "scanned_at": "2025-05-09T01:03:06.265Z",
  "error": null,
  "grade": "C",
  "response_headers": {
    "date": "Fri, 09 May 2025 01:03:07 GMT",
    "server": "Apache",
    "connection": "close",
    "set-cookie": "JSESSIONID=388EB5B0B2C00D9E2308620E76F6221A; Path=/; Secure; HttpOnly,COOKIE_SUPPORT=true; Max-Age=31536000; Expires=Sat, 09-May-2026 01:03:07 GMT; Path=/; Secure; HttpOnly,GUEST_LANGUAGE_ID=es_ES; Max-Age=31536000; Expires=Sat, 09-May-2026 01:03:07 GMT; Path=/; Secure; HttpOnly",
    "content-type": "text/html;charset=UTF-8",
    "x-frame-options": "SAMEORIGIN",
    "x-xss-protection": "1",
    "transfer-encoding": "chunked",
    "x-content-type-options": "nosniff",
    "content-security-policy": "upgrade-insecure-requests;"
  },
  "score": 55,
  "status_code": 200,
  "tests_failed": 3,
  "tests_passed": 7,
  "tests_quantity": 10
}