{
  "algorithm_version": 2,
  "end_time": "Sat, 25 Feb 2023 00:56:03 GMT",
  "grade": "F",
  "hidden": false,
  "likelihood_indicator": "MEDIUM",
  "response_headers": {
    "Age": "8",
    "Cache-Control": "max-age=600, must-revalidate",
    "Connection": "Keep-Alive",
    "Content-Length": "83876",
    "Content-Type": "text/html;charset=ISO-8859-1",
    "Date": "Sat, 25 Feb 2023 00:56:18 GMT",
    "Keep-Alive": "timeout=5, max=99",
    "Last-Modified": "Sat, 25 Feb 2023 00:56:12 GMT",
    "Server": "Apache/2.4.43 (Unix) OpenSSL/1.0.2k-fips mod_jk/1.2.46",
    "Set-Cookie": "JSESSIONID=2EB697C69E14FC8BEFFB6DBD8C901C85; Path=/; Secure"
  },
  "scan_id": 34665604,
  "score": 0,
  "start_time": "Sat, 25 Feb 2023 00:55:24 GMT",
  "state": "FINISHED",
  "status_code": 200,
  "tests_failed": 8,
  "tests_passed": 4,
  "tests_quantity": 12
}