{
  "id": 82425991,
  "algorithm_version": 5,
  "scanned_at": "2026-01-08T01:09:57.031Z",
  "error": null,
  "grade": "B-",
  "response_headers": {
    "date": "Thu, 08 Jan 2026 01:09:59 GMT",
    "vary": "Accept-Encoding",
    "x-cdn": "Imperva",
    "upgrade": "h2",
    "x-iinfo": "14-254366067-254366068 NNNN CT(181 1776 0) RT(1767834597057 21) q(0 0 20 5) r(22 22) U12",
    "connection": "Upgrade, close",
    "set-cookie": "visid_incap_171420=cIxRwOVIQjS5k5yvmlwSiuQDX2kAAAAAQUIPAAAAAABudmT5RjVGtra0nj9xLdWH; expires=Thu, 07 Jan 2027 08:27:28 GMT; HttpOnly; path=/; Domain=.grancanaria.com; Secure; SameSite=None,nlbi_171420=Hy8yPc/gjSiAHqdO3tof+wAAAACwT/3lxO4XS7c5ISXK1xyv; HttpOnly; path=/; Domain=.grancanaria.com; Secure; SameSite=None,incap_ses_227_171420=N0bUGI+Eol2YyVOux3cmA+YDX2kAAAAAD6KhvKhE42HmVOEpxMF0IA==; path=/; Domain=.grancanaria.com; Secure; SameSite=None",
    "content-type": "text/html",
    "accept-ranges": "bytes",
    "last-modified": "Mon, 18 Apr 2022 08:21:00 GMT",
    "referrer-policy": "no-referrer-when-downgrade",
    "x-frame-options": "SAMEORIGIN",
    "x-xss-protection": "1; mode=block",
    "transfer-encoding": "chunked",
    "x-content-type-options": "nosniff",
    "strict-transport-security": "max-age=31536000"
  },
  "score": 65,
  "status_code": 200,
  "tests_failed": 3,
  "tests_passed": 7,
  "tests_quantity": 10
}