{
  "id": 83173920,
  "algorithm_version": 5,
  "scanned_at": "2026-01-15T01:08:05.466Z",
  "error": null,
  "grade": "B",
  "response_headers": {
    "date": "Thu, 15 Jan 2026 01:08:05 GMT",
    "vary": "Accept-Encoding",
    "server": "Apache",
    "expires": "Sat, 1 Jul 2000 05:00:00 GMT",
    "upgrade": "h2",
    "connection": "Upgrade, close",
    "content-type": "text/html; charset=UTF-8",
    "cache-control": "no-cache, must-revalidate",
    "content-length": "13791",
    "x-frame-options": "SAMEORIGIN",
    "x-xss-protection": "1; mode=block",
    "x-content-type-options": "nosniff",
    "strict-transport-security": "max-age=31536000;"
  },
  "score": 75,
  "status_code": 200,
  "tests_failed": 1,
  "tests_passed": 9,
  "tests_quantity": 10
}