{
  "id": 100962056,
  "algorithm_version": 5,
  "scanned_at": "2026-06-15T02:58:14.923Z",
  "error": null,
  "grade": "D-",
  "response_headers": {
    "nel": "{\"report_to\":\"cf-nel\",\"success_fraction\":0.0,\"max_age\":604800}",
    "date": "Mon, 15 Jun 2026 02:58:15 GMT",
    "link": "<https://www.mirandadeebro.es/wp-json/>; rel=\"https://api.w.org/\", <https://www.mirandadeebro.es/wp-json/wp/v2/pages/6367>; rel=\"alternate\"; title=\"JSON\"; type=\"application/json\", <https://www.mirandadeebro.es/>; rel=shortlink",
    "vary": "Accept-Encoding",
    "cf-ray": "a0be4fdb79af7651-SEA",
    "server": "cloudflare",
    "alt-svc": "h3=\":443\"; ma=86400",
    "report-to": "{\"group\":\"cf-nel\",\"max_age\":604800,\"endpoints\":[{\"url\":\"https://a.nel.cloudflare.com/report/v4?s=qzGn2sLeA9cQJ05jD4TYa%2Bu4wFBKxqjQ%2BdoAwx5dhTDaqt0S6BmptRA5eWPXvK2%2F7mTbhMqVyfxA12lADr6%2BzTvlksWuZFXUsYQjLFaKktAzCECL3CLdJIGEZjQ6c8yv54svT87T\"}]}",
    "cf-apo-via": "tcache",
    "connection": "close",
    "content-type": "text/html; charset=UTF-8",
    "cf-edge-cache": "cache,platform=wordpress",
    "last-modified": "Mon, 15 Jun 2026 02:58:15 GMT",
    "server-timing": "cfCacheStatus;desc=\"HIT\", cfEdge;dur=189,cfOrigin;dur=0",
    "cf-cache-status": "HIT",
    "transfer-encoding": "chunked"
  },
  "score": 25,
  "status_code": 200,
  "tests_failed": 5,
  "tests_passed": 5,
  "tests_quantity": 10
}