{
  "algorithm_version": 2,
  "end_time": "Mon, 26 Jun 2023 00:13:51 GMT",
  "grade": "F",
  "hidden": false,
  "likelihood_indicator": "MEDIUM",
  "response_headers": {
    "Connection": "close",
    "Content-Type": "text/html;charset=ISO-8859-1",
    "Date": "Mon, 26 Jun 2023 00:13:44 GMT",
    "Server": "Apache-Coyote/1.1",
    "Set-Cookie": "JSESSIONID=6E0187E7A936C27C7F5B500EBFFA7B3B; Path=/webdinamica/; HttpOnly",
    "Transfer-Encoding": "chunked"
  },
  "scan_id": 38979072,
  "score": 0,
  "start_time": "Mon, 26 Jun 2023 00:13:38 GMT",
  "state": "FINISHED",
  "status_code": 200,
  "tests_failed": 7,
  "tests_passed": 5,
  "tests_quantity": 12
}