{
  "algorithm_version": 3,
  "end_time": "Fri, 19 Apr 2024 00:41:23 GMT",
  "grade": "F",
  "hidden": false,
  "likelihood_indicator": "MEDIUM",
  "response_headers": {
    "Cache-Control": "no-store, no-cache, must-revalidate",
    "Connection": "Keep-Alive",
    "Content-Encoding": "gzip",
    "Content-Length": "5645",
    "Content-Type": "text/html; charset=utf-8",
    "Date": "Fri, 19 Apr 2024 00:41:18 GMT",
    "Expect-CT": "enforce, max-age=43200",
    "Expires": "Thu, 19 Nov 1981 08:52:00 GMT",
    "Keep-Alive": "timeout=5, max=100",
    "Pragma": "no-cache",
    "Referrer-Policy": "no-referrer",
    "Server": "Apache",
    "Set-Cookie": "PHPSESSID=7522b8nurlirb7jsu95v82gr7i; path=/",
    "Vary": "Accept-Encoding,User-Agent",
    "X-Content-Type-Options": "nosniff",
    "X-Frame-Options": "SAMEORIGIN",
    "X-Permitted-Cross-Domain-Policies": "none",
    "X-Powered-By": "PHP/7.1.33",
    "X-XSS-Protection": "1; mode=block"
  },
  "scan_id": 50175557,
  "score": 0,
  "start_time": "Fri, 19 Apr 2024 00:41:14 GMT",
  "state": "FINISHED",
  "status_code": 200,
  "tests_failed": 4,
  "tests_passed": 7,
  "tests_quantity": 11
}