{
  "algorithm_version": 3,
  "end_time": "Wed, 08 May 2024 00:34:56 GMT",
  "grade": "D-",
  "hidden": false,
  "likelihood_indicator": "MEDIUM",
  "response_headers": {
    "Accept-Ranges": "bytes",
    "Age": "16",
    "Alt-Svc": "h3=\":443\"; ma=86400",
    "Cache-Control": "max-age=60, public",
    "Connection": "keep-alive",
    "Content-Encoding": "gzip",
    "Content-Type": "text/html; charset=UTF-8",
    "Date": "Wed, 08 May 2024 00:34:37 GMT",
    "Expires": "Wed, 08 May 2024 00:32:03 GMT",
    "Transfer-Encoding": "chunked",
    "Vary": "Accept-Encoding",
    "Via": "1.1 0bb842bd5868b86440983b936bb0adee.cloudfront.net (CloudFront)",
    "X-Amz-Cf-Id": "kYnWGa-NvtuSbkQ2ol5gutLYlG1w_q_xTEhd4tcM4ttERC1MviKCaQ==",
    "X-Amz-Cf-Pop": "SEA19-C1",
    "X-Cache": "Hit from cloudfront"
  },
  "scan_id": 50803634,
  "score": 25,
  "start_time": "Wed, 08 May 2024 00:34:53 GMT",
  "state": "FINISHED",
  "status_code": 200,
  "tests_failed": 5,
  "tests_passed": 6,
  "tests_quantity": 11
}