{
  "algorithm_version": 2,
  "end_time": "Sun, 17 Oct 2021 00:06:39 GMT",
  "grade": "F",
  "hidden": false,
  "likelihood_indicator": "MEDIUM",
  "response_headers": {
    "Accept-Ranges": "bytes",
    "Cache-Control": "max-age=172800",
    "Connection": "keep-alive, Keep-Alive",
    "Content-Encoding": "gzip",
    "Content-Length": "6913",
    "Content-Type": "text/html; charset=utf-8",
    "Date": "Sun, 17 Oct 2021 00:06:26 GMT",
    "ETag": "\"1790893-87bb-5cd954c4206e1-gzip\"",
    "Expires": "Tue, 19 Oct 2021 00:06:26 GMT",
    "Keep-Alive": "timeout=5, max=150",
    "Last-Modified": "Tue, 05 Oct 2021 06:39:56 GMT",
    "Server": "Apache",
    "Vary": "Accept-Encoding,User-Agent"
  },
  "scan_id": 22067264,
  "score": 15,
  "start_time": "Sun, 17 Oct 2021 00:06:23 GMT",
  "state": "FINISHED",
  "status_code": 200,
  "tests_failed": 6,
  "tests_passed": 6,
  "tests_quantity": 12
}