{
  "algorithm_version": 2,
  "end_time": "Wed, 06 Jul 2022 01:00:54 GMT",
  "grade": "D-",
  "hidden": false,
  "likelihood_indicator": "MEDIUM",
  "response_headers": {
    "Cache-Control": "private, max-age=0",
    "Content-Length": "173731",
    "Content-Type": "text/html; charset=utf-8",
    "Date": "Wed, 06 Jul 2022 01:00:19 GMT",
    "ETag": "\"1657069217:dtagent10241220422021336j5N0\"",
    "Expires": "Tue, 21 Jun 2022 01:00:17 GMT",
    "Last-Modified": "Wed, 06 Jul 2022 01:00:16 GMT",
    "SPIisLatency": "0",
    "SPRequestDuration": "2986",
    "SPRequestGuid": "27334ea0-d5e3-2055-d657-14788cc78284",
    "Server-Timing": "dtSInfo;desc=\"0\", dtRpid;desc=\"-1773674323\"",
    "Set-Cookie": "SearchSession=eea538c1%2D62da%2D430e%2D8c83%2D07ed291904c6; path=/es; secure; HttpOnly; SameSite=None",
    "Strict-Transport-Security": "max-age=10886400",
    "X-Content-Type-Options": "nosniff",
    "X-FRAME-OPTIONS": "SAMEORIGIN",
    "X-MS-InvokeApp": "1; RequireReadOnly",
    "X-OneAgent-JS-Injection": "true",
    "X-SharePointHealthScore": "XX",
    "X-XSS-Protection": "1; mode=block",
    "X-ruxit-JS-Agent": "true",
    "request-id": "27334ea0-d5e3-2055-d657-14788cc78284",
    "spp": "4de78ca9-2f5f-4a7f-903e-5eee9bc5885a"
  },
  "scan_id": 27620284,
  "score": 25,
  "start_time": "Wed, 06 Jul 2022 01:00:09 GMT",
  "state": "FINISHED",
  "status_code": 200,
  "tests_failed": 3,
  "tests_passed": 9,
  "tests_quantity": 12
}