{
  "algorithm_version": 2,
  "end_time": "Mon, 03 Jan 2022 00:07:47 GMT",
  "grade": "F",
  "hidden": false,
  "likelihood_indicator": "MEDIUM",
  "response_headers": {
    "Cache-Control": "private",
    "Content-Encoding": "gzip",
    "Content-Length": "31680",
    "Content-Type": "text/html; charset=utf-8",
    "Date": "Mon, 03 Jan 2022 00:07:44 GMT",
    "Server": "Microsoft-IIS/10.0",
    "Set-Cookie": "ASP.NET_SessionId=x1ndp0obbxsyb3vxouvjtfwf; path=/; HttpOnly; SameSite=Lax",
    "Vary": "Accept-Encoding",
    "X-AspNet-Version": "4.0.30319"
  },
  "scan_id": 23628335,
  "score": 0,
  "start_time": "Mon, 03 Jan 2022 00:07:41 GMT",
  "state": "FINISHED",
  "status_code": 200,
  "tests_failed": 7,
  "tests_passed": 5,
  "tests_quantity": 12
}