{
  "id": 103384718,
  "algorithm_version": 5,
  "scanned_at": "2026-06-26T02:39:46.130Z",
  "error": null,
  "grade": "C+",
  "response_headers": {
    "date": "Fri, 26 Jun 2026 02:39:53 GMT",
    "vary": "Accept-Encoding",
    "pragma": "no-cache",
    "server": "nginx",
    "expires": "Thu, 01 Jan 1970 00:00:00 GMT",
    "connection": "close",
    "set-cookie": "JSESSIONID=D97387919384C0B00CF50DFFDA1857D4.araneo74; Path=/; Secure; HttpOnly,COOKIE_SUPPORT=true; Max-Age=31536000; Expires=Sat, 26 Jun 2027 02:39:53 GMT; Path=/; Secure; HttpOnly,GUEST_LANGUAGE_ID=es_ES; Max-Age=31536000; Expires=Sat, 26 Jun 2027 02:39:53 GMT; Path=/; Secure; HttpOnly,cookiesession1=678A8C50B4EB5229F572D44D29EFC813;Expires=Sat, 26 Jun 2027 02:39:54 GMT;Path=/;HttpOnly",
    "content-type": "text/html;charset=UTF-8",
    "cache-control": "private, no-cache, no-store, must-revalidate",
    "content-length": "45997",
    "liferay-portal": "Liferay Community Edition Portal",
    "x-frame-options": "SAMEORIGIN",
    "x-content-type-options": "nosniff",
    "strict-transport-security": "max-age=31536000"
  },
  "score": 60,
  "status_code": 200,
  "tests_failed": 3,
  "tests_passed": 7,
  "tests_quantity": 10
}