{
  "id": 61430982,
  "algorithm_version": 4,
  "scanned_at": "2025-04-15T01:02:09.712Z",
  "error": null,
  "grade": "D-",
  "response_headers": {
    "age": "0",
    "date": "Tue, 15 Apr 2025 01:02:10 GMT",
    "vary": "X-Forwarded-Proto,Accept-Encoding,User-Agent",
    "server": "HTTPd",
    "expires": "Tue, 15 Apr 2025 01:02:10 GMT",
    "connection": "close",
    "content-type": "text/html; charset=UTF-8",
    "accept-ranges": "bytes",
    "cache-control": "max-age=0",
    "last-modified": "Mon, 14 Apr 2025 23:13:56 GMT",
    "content-length": "165219"
  },
  "score": 25,
  "status_code": 200,
  "tests_failed": 5,
  "tests_passed": 5,
  "tests_quantity": 10
}