{
  "algorithm_version": 3,
  "end_time": "Tue, 30 Jul 2024 01:01:40 GMT",
  "grade": "F",
  "hidden": false,
  "likelihood_indicator": "MEDIUM",
  "response_headers": {
    "Accept-Ranges": "bytes",
    "Age": "52",
    "Cache-Control": "no-store, no-cache, must-revalidate, post-check=0, pre-check=0",
    "Connection": "keep-alive",
    "Content-Encoding": "gzip",
    "Content-Length": "17622",
    "Content-Type": "text/html; charset=UTF-8",
    "Date": "Tue, 30 Jul 2024 01:01:26 GMT",
    "Expires": "Thu, 19 Nov 1981 08:52:00 GMT",
    "Pragma": "no-cache",
    "Server": "HTTPd",
    "Set-Cookie": "PHPSESSID=98k0qn390mehh4r0973crd8vl1; path=/",
    "Vary": "Accept-Encoding"
  },
  "scan_id": 53892380,
  "score": 0,
  "start_time": "Tue, 30 Jul 2024 01:01:24 GMT",
  "state": "FINISHED",
  "status_code": 200,
  "tests_failed": 6,
  "tests_passed": 4,
  "tests_quantity": 10
}