{
  "algorithm_version": 2,
  "end_time": "Sun, 23 Jul 2023 01:25:08 GMT",
  "grade": "B-",
  "hidden": false,
  "likelihood_indicator": "MEDIUM",
  "response_headers": {
    "Cache-Control": "no-cache",
    "Content-Encoding": "gzip",
    "Content-Length": "16887",
    "Content-Type": "text/html; charset=utf-8",
    "Date": "Sun, 23 Jul 2023 01:25:01 GMT",
    "Expires": "-1",
    "Pragma": "no-cache",
    "SPIisLatency": "0",
    "SPRequestDuration": "1707",
    "SPRequestGuid": "6628c9a0-9269-b025-e01d-cc12344482ba",
    "Server": "Microsoft-IIS/8.0",
    "Set-Cookie": "lang=es; Expires=Sat, 23-Jul-2033 01:25:00 GMT; Path=/; Secure; HttpOnly",
    "Strict-Transport-Security": "max-age=31536000; includeSubDomains; preload",
    "Vary": "Accept-Encoding",
    "X-AspNet-Version": "4.0.30319",
    "X-Content-Type-Options": "nosniff",
    "X-FRAME-OPTIONS": "SAMEORIGIN",
    "X-MS-InvokeApp": "1; RequireReadOnly",
    "X-Powered-By": "ASP.NET",
    "X-SharePointHealthScore": "0",
    "request-id": "6628c9a0-9269-b025-e01d-cc12344482ba"
  },
  "scan_id": 40005158,
  "score": 65,
  "start_time": "Sun, 23 Jul 2023 01:24:52 GMT",
  "state": "FINISHED",
  "status_code": 200,
  "tests_failed": 2,
  "tests_passed": 10,
  "tests_quantity": 12
}