{
  "algorithm_version": 2,
  "end_time": "Tue, 19 Sep 2023 00:11:07 GMT",
  "grade": "F",
  "hidden": false,
  "likelihood_indicator": "MEDIUM",
  "response_headers": {
    "Accept-Ranges": "bytes",
    "Age": "112",
    "Cache-Control": "max-age=0, no-cache,must-revalidate",
    "Connection": "keep-alive",
    "Content-Length": "158261",
    "Content-Type": "text/html; charset=UTF-8",
    "Date": "Tue, 19 Sep 2023 00:11:05 GMT",
    "Last-Modified": "Tue, 19 Sep 2023 00:11:05 GMT",
    "Pragma": "public",
    "Vary": "Accept-Encoding",
    "X-Cache": "HIT, MISS",
    "X-Cache-Hits": "5, 0"
  },
  "scan_id": 42289107,
  "score": 15,
  "start_time": "Tue, 19 Sep 2023 00:11:02 GMT",
  "state": "FINISHED",
  "status_code": 200,
  "tests_failed": 6,
  "tests_passed": 6,
  "tests_quantity": 12
}