{
  "id": 86776392,
  "algorithm_version": 5,
  "scanned_at": "2026-03-01T01:42:57.616Z",
  "error": null,
  "grade": "F",
  "response_headers": {
    "date": "Sun, 01 Mar 2026 01:42:58 GMT",
    "pragma": "no-cache",
    "server": "Apache",
    "expires": "Thu, 01 Jan 1970 00:00:00 GMT",
    "connection": "close",
    "set-cookie": "GUEST_LANGUAGE_ID=eu_ES; Max-Age=31536000; Expires=Mon, 01 Mar 2027 01:42:58 GMT; Path=/; HttpOnly,COOKIE_SUPPORT=true; Max-Age=31536000; Expires=Mon, 01 Mar 2027 01:42:58 GMT; Path=/; HttpOnly",
    "content-type": "text/html;charset=UTF-8",
    "cache-control": "private, no-cache, no-store, must-revalidate",
    "liferay-portal": "Liferay Digital Experience Platform",
    "x-frame-options": "SAMEORIGIN",
    "x-ua-compatible": "IE=edge",
    "x-xss-protection": "1",
    "transfer-encoding": "chunked",
    "x-content-type-options": "nosniff"
  },
  "score": 10,
  "status_code": 200,
  "tests_failed": 4,
  "tests_passed": 6,
  "tests_quantity": 10
}