{
  "id": 84434707,
  "algorithm_version": 5,
  "scanned_at": "2026-01-28T01:10:22.259Z",
  "error": null,
  "grade": "B",
  "response_headers": {
    "age": "0",
    "date": "Wed, 28 Jan 2026 01:10:23 GMT",
    "vary": ", Accept-Encoding",
    "tp-cache": "miss",
    "connection": "close",
    "set-cookie": "JSESSIONID=7789423C71BEBEA1AC8D7D297BA69688; Path=/; Secure; HttpOnly,COOKIE_SUPPORT=true; Expires=Sun, 11-Sep-2072 03:52:30 GMT; Path=/; Secure; HttpOnly,GUEST_LANGUAGE_ID=es_ES; Expires=Sun, 11-Sep-2072 03:52:30 GMT; Path=/; Secure; HttpOnly,iqY4L9kU=ffffffffc3a000ba45525d5f4f58455e445a4a42378b;expires=Wed, 28-Jan-2026 01:40:23 GMT;path=/;secure;httponly",
    "content-type": "text/html;charset=UTF-8",
    "accept-ranges": "bytes",
    "liferay-portal": "Liferay Portal Community Edition 6.2 CE GA6 (Newton / Build 6205 / January 6, 2016)",
    "x-frame-options": "SAMEORIGIN",
    "x-xss-protection": "1",
    "transfer-encoding": "chunked",
    "x-content-type-options": "nosniff",
    "strict-transport-security": "max-age=157680000"
  },
  "score": 75,
  "status_code": 200,
  "tests_failed": 1,
  "tests_passed": 9,
  "tests_quantity": 10
}