{
  "algorithm_version": 3,
  "end_time": "Wed, 20 Mar 2024 05:12:45 GMT",
  "grade": "C",
  "hidden": true,
  "likelihood_indicator": "MEDIUM",
  "response_headers": {
    "Cache-Control": "max-age=3600, public",
    "Connection": "Keep-Alive",
    "Content-Encoding": "gzip",
    "Content-Length": "18133",
    "Content-Type": "text/html; charset=UTF-8",
    "Content-language": "es",
    "Date": "Tue, 19 Mar 2024 14:49:24 GMT",
    "ETag": "\"1710911597-gzip\"",
    "Expires": "Sun, 19 Nov 1978 05:00:00 GMT",
    "Keep-Alive": "timeout=5, max=100",
    "Last-Modified": "Wed, 20 Mar 2024 05:13:17 GMT",
    "Server": "Apache/2.4.37 (Red Hat Enterprise Linux) OpenSSL/1.1.1k",
    "Vary": "Cookie,Accept-Encoding",
    "X-Content-Type-Options": "nosniff",
    "X-Drupal-Dynamic-Cache": "HIT",
    "X-Frame-Options": "SAMEORIGIN",
    "X-Generator": "Drupal 10 (https://www.drupal.org)",
    "X-Powered-By": "PHP/8.2.17"
  },
  "scan_id": 49073361,
  "score": 55,
  "start_time": "Wed, 20 Mar 2024 05:12:39 GMT",
  "state": "FINISHED",
  "status_code": 200,
  "tests_failed": 2,
  "tests_passed": 9,
  "tests_quantity": 11
}