{
  "id": 79817498,
  "algorithm_version": 5,
  "scanned_at": "2025-12-08T01:05:13.148Z",
  "error": null,
  "grade": "C+",
  "response_headers": {
    "date": "Mon, 08 Dec 2025 01:05:20 GMT",
    "vary": "Accept-Encoding",
    "pragma": "no-cache",
    "server": "nginx",
    "expires": "Thu, 31 Dec 2037 23:55:55 GMT",
    "connection": "close",
    "set-cookie": "JSESSIONID=85F5A3E4D3C9D9ED14E26ACB3BC8AB2C; Path=/; HttpOnly,COOKIE_SUPPORT=true; Max-Age=31536000; Expires=Tue, 08-Dec-2026 01:05:13 GMT; Path=/; HttpOnly,GUEST_LANGUAGE_ID=en_GB; Max-Age=31536000; Expires=Tue, 08-Dec-2026 01:05:13 GMT; Path=/; HttpOnly",
    "content-type": "text/html;charset=UTF-8",
    "cache-control": "max-age=315360000, public, max-age=31536000",
    "liferay-portal": "Liferay Digital Experience Platform",
    "x-frame-options": "SAMEORIGIN",
    "x-xss-protection": "1",
    "transfer-encoding": "chunked",
    "x-content-type-options": "nosniff",
    "strict-transport-security": "max-age=31536000; includeSubDomains"
  },
  "score": 60,
  "status_code": 200,
  "tests_failed": 3,
  "tests_passed": 7,
  "tests_quantity": 10
}