{
  "id": 92840401,
  "algorithm_version": 5,
  "scanned_at": "2026-04-21T01:55:49.187Z",
  "error": null,
  "grade": "F",
  "response_headers": {
    "date": "Tue, 21 Apr 2026 01:55:50 GMT",
    "vary": "Accept-Encoding",
    "server": "Apache",
    "connection": "close",
    "set-cookie": "JSESSIONID=7AACCB81752038572B82F4C118C677FB; Path=/portal_localweb",
    "content-type": "text/html;charset=ISO-8859-1",
    "content-length": "4976",
    "content-language": "gl"
  },
  "score": 0,
  "status_code": 200,
  "tests_failed": 7,
  "tests_passed": 3,
  "tests_quantity": 10
}