{
  "algorithm_version": 2,
  "end_time": "Sat, 10 Apr 2021 00:27:41 GMT",
  "grade": "D-",
  "hidden": false,
  "likelihood_indicator": "MEDIUM",
  "response_headers": {
    "Accept-Ranges": "bytes",
    "Connection": "Upgrade, Keep-Alive",
    "Content-Encoding": "gzip",
    "Content-Type": "text/html",
    "Date": "Sat, 10 Apr 2021 00:27:37 GMT",
    "Keep-Alive": "timeout=15, max=100",
    "Last-Modified": "Tue, 23 Feb 2021 12:02:50 GMT",
    "Referrer-Policy": "no-referrer-when-downgrade",
    "Set-Cookie": "nlbi_171420=jvOZWFdUpio0uHaY3tof+wAAAACnW/Vs7LJ35u36BAUGOr9J; path=/; Domain=.grancanaria.com; Secure; SameSite=None, visid_incap_171420=i21TzLcUTLuwDXNWDEYd3/jwcGAAAAAAQUIPAAAAAADv659nNaZoDHPENrES4OlQ; expires=Sat, 09 Apr 2022 08:21:28 GMT; HttpOnly; path=/; Domain=.grancanaria.com; Secure; SameSite=None, incap_ses_1163_171420=Tgb2fyxgCRbQI/Mxms4jEPnwcGAAAAAA5VO/zf/vCt4dsVlPYCjs+w==; path=/; Domain=.grancanaria.com; Secure; SameSite=None",
    "Strict-Transport-Security": "max-age=31536000",
    "Transfer-Encoding": "chunked",
    "Upgrade": "h2",
    "Vary": "Accept-Encoding",
    "X-CDN": "Imperva",
    "X-Content-Type-Options": "nosniff",
    "X-Frame-Options": "SAMEORIGIN",
    "X-Iinfo": "5-68214543-68214545 nNNN RT(1618014457201 22) q(0 0 3 3) r(4 5) U12",
    "X-XSS-Protection": "1; mode=block"
  },
  "scan_id": 18609171,
  "score": 25,
  "start_time": "Sat, 10 Apr 2021 00:27:34 GMT",
  "state": "FINISHED",
  "status_code": 200,
  "tests_failed": 2,
  "tests_passed": 10,
  "tests_quantity": 12
}