{
  "id": 85768759,
  "algorithm_version": 5,
  "scanned_at": "2026-02-15T01:29:48.093Z",
  "error": null,
  "grade": "F",
  "response_headers": {
    "date": "Sun, 15 Feb 2026 01:29:47 GMT",
    "etag": "\"869b3089ca9c1d242c433ad8e61c071f\"",
    "vary": "Accept-Encoding",
    "pragma": "public",
    "server": "Microsoft-IIS/10.0",
    "expires": "Sun, 15 Feb 2026 02:29:48 GMT",
    "connection": "close",
    "content-type": "text/html; charset=UTF-8",
    "x-powered-by": "PHP/8.3.29, ASP.NET",
    "cache-control": "max-age=3600, public",
    "last-modified": "Sun, 15 Feb 2026 01:29:48 GMT",
    "content-length": "26365"
  },
  "score": 0,
  "status_code": 200,
  "tests_failed": 5,
  "tests_passed": 5,
  "tests_quantity": 10
}