{
  "id": 71331391,
  "algorithm_version": 4,
  "scanned_at": "2025-08-31T01:04:40.750Z",
  "error": null,
  "grade": "F",
  "response_headers": {
    "age": "59062",
    "nel": "{\"success_fraction\":0,\"report_to\":\"cf-nel\",\"max_age\":604800}",
    "date": "Sun, 31 Aug 2025 01:04:40 GMT",
    "link": "<https://www.mirandadeebro.es/wp-json/>; rel=\"https://api.w.org/\", <https://www.mirandadeebro.es/wp-json/wp/v2/pages/6367>; rel=\"alternate\"; title=\"JSON\"; type=\"application/json\", <https://www.mirandadeebro.es/>; rel=shortlink",
    "vary": "Accept-Encoding",
    "cf-ray": "97789d7ee8a97627-SEA",
    "server": "cloudflare",
    "report-to": "{\"endpoints\":[{\"url\":\"https:\\/\\/a.nel.cloudflare.com\\/report\\/v4?s=UUod3nstGC3dLD9uUlOmgARGwInfQepWY7caJaoUebj%2BYT5sAJ%2BD3Buhz7o%2ByCQTk0oI6xis8hwwihvPZ3k2AYZzzEvcV%2FOyhJadBHWxNVNNjh%2BWpMKPIDJNAr4YSMJjzAb5%2FYPO\"}],\"group\":\"cf-nel\",\"max_age\":604800}",
    "cf-apo-via": "tcache",
    "connection": "close",
    "content-type": "text/html; charset=UTF-8",
    "cache-control": "max-age=14400",
    "cf-edge-cache": "cache,platform=wordpress",
    "last-modified": "Sat, 30 Aug 2025 05:14:47 GMT",
    "server-timing": "cfCacheStatus;desc=\"HIT\", cfOrigin;dur=0,cfEdge;dur=49, cfL4;desc=\"?proto=TCP&rtt=7398&min_rtt=7391&rtt_var=2777&sent=5&recv=5&lost=0&retrans=0&sent_bytes=2840&recv_bytes=780&delivery_rate=571505&cwnd=252&unsent_bytes=0&cid=04c4ed751bc06aad&ts=65&x=0\"",
    "cf-cache-status": "HIT",
    "transfer-encoding": "chunked"
  },
  "score": 5,
  "status_code": 200,
  "tests_failed": 6,
  "tests_passed": 4,
  "tests_quantity": 10
}