{
  "algorithm_version": 2,
  "end_time": "Thu, 21 Oct 2021 00:16:20 GMT",
  "grade": "F",
  "hidden": false,
  "likelihood_indicator": "MEDIUM",
  "response_headers": {
    "Accept-Ranges": "bytes",
    "Content-Length": "105",
    "Content-Location": "http://www.navarra.es/Default.htm",
    "Content-Type": "text/html",
    "Date": "Thu, 21 Oct 2021 00:16:12 GMT",
    "ETag": "\"d9d5d17f93efcb1:32e7d\"",
    "Last-Modified": "Thu, 31 Mar 2011 11:05:09 GMT",
    "Server": "Microsoft-IIS/6.0",
    "Set-Cookie": "GN=!D7vduBqIegS2L7petkLXXr0XOw99UNCPq558n9RtwcQD6lLGkAz75qooag/NlvZQm/dldGcfwldcMA==; path=/; Httponly; Secure"
  },
  "scan_id": 22171535,
  "score": 0,
  "start_time": "Thu, 21 Oct 2021 00:16:07 GMT",
  "state": "FINISHED",
  "status_code": 200,
  "tests_failed": 7,
  "tests_passed": 5,
  "tests_quantity": 12
}