{
  "algorithm_version": 3,
  "end_time": "Fri, 12 Apr 2024 00:11:41 GMT",
  "grade": "F",
  "hidden": false,
  "likelihood_indicator": "MEDIUM",
  "response_headers": {
    "CF-Cache-Status": "DYNAMIC",
    "CF-RAY": "872efff2ab437536-SEA",
    "Connection": "keep-alive",
    "Content-Encoding": "gzip",
    "Content-Type": "text/html; charset=UTF-8",
    "Date": "Fri, 12 Apr 2024 00:11:34 GMT",
    "Last-Modified": "Thu, 11 Apr 2024 16:47:07 GMT",
    "NEL": "{\"success_fraction\":0,\"report_to\":\"cf-nel\",\"max_age\":604800}",
    "Report-To": "{\"endpoints\":[{\"url\":\"https:\\/\\/a.nel.cloudflare.com\\/report\\/v4?s=wrM16uRsFYAIDKTDYO1%2Bjt8sRDioqjemWLKgnsE9GBAfYGNsjx75nOsgo9%2F0OdjRCttg0KFXA9Cp7W0iZtFNjTbQWuWM%2BfnA1Si084LcYeomyn3o0Y1yAlbgFvv3\"}],\"group\":\"cf-nel\",\"max_age\":604800}",
    "Server": "cloudflare",
    "Transfer-Encoding": "chunked",
    "Vary": "Accept-Encoding"
  },
  "scan_id": 49932562,
  "score": 0,
  "start_time": "Fri, 12 Apr 2024 00:11:32 GMT",
  "state": "FINISHED",
  "status_code": 200,
  "tests_failed": 6,
  "tests_passed": 5,
  "tests_quantity": 11
}