{
  "algorithm_version": 2,
  "end_time": "Tue, 12 Sep 2023 00:10:43 GMT",
  "grade": "D-",
  "hidden": false,
  "likelihood_indicator": "MEDIUM",
  "response_headers": {
    "Cache-Control": "private",
    "Connection": "Keep-Alive",
    "Content-Encoding": "gzip",
    "Content-Length": "25115",
    "Content-Security-Policy": "default-src 'none'; script-src 'self' https://platform.twitter.com https://cdn.jsdelivr.net https://cdnjs.cloudflare.com https://cdn.datatables.net https://www.google.com https://www.gstatic.com https://az416426.vo.msecnd.net 'unsafe-inline' 'unsafe-eval'; img-src 'self'; frame-src 'self' https://correo.emvs.es https://www3.emvs.es https://syndication.twitter.com https://platform.twitter.com https://www.youtube.com https://www.google.com https://view.genial.ly https://shares.enetres.net https://iframe.dacast.com  'unsafe-inline'; style-src 'self' https://cdn.jsdelivr.net https://fonts.googleapis.com 'unsafe-inline'; font-src 'self' data: https://fonts.gstatic.com; connect-src 'self' https://dc.services.visualstudio.com; media-src 'self'; manifest-src 'self'",
    "Content-Type": "text/html; charset=utf-8",
    "Date": "Tue, 12 Sep 2023 00:10:40 GMT",
    "Expires": "Tue, 12 Sep 2023 00:13:39 GMT",
    "MicrosoftSharePointTeamServices": "16.0.0.10396",
    "Referrer-Policy": "strict-origin-when-cross-origin",
    "SPIisLatency": "0",
    "SPRequestDuration": "21",
    "SPRequestGuid": "6a8ed9a0-fcfc-a09e-d641-7ead422de9cb",
    "Server": "Web",
    "Strict-Transport-Security": "max-age=31536000; includeSubDomains",
    "Vary": "*",
    "X-Content-Type-Options": "nosniff",
    "X-FRAME-OPTIONS": "SAMEORIGIN",
    "X-MS-InvokeApp": "1; RequireReadOnly",
    "X-Powered-By": "",
    "X-SharePointHealthScore": "0",
    "X-XSS-Protection": "0",
    "request-id": "6a8ed9a0-fcfc-a09e-d641-7ead422de9cb"
  },
  "scan_id": 42016441,
  "score": 25,
  "start_time": "Tue, 12 Sep 2023 00:10:35 GMT",
  "state": "FINISHED",
  "status_code": 200,
  "tests_failed": 5,
  "tests_passed": 7,
  "tests_quantity": 12
}